whatssup/__init__.py
whatssup/timemon.py
whatssup-0.0.5.dist-info/LICENSE
whatssup-0.0.5.dist-info/METADATA
whatssup-0.0.5.dist-info/WHEEL
whatssup-0.0.5.dist-info/entry_points.txt
whatssup-0.0.5.dist-info/top_level.txt
whatssup-0.0.5.dist-info/RECORD
