Metadata-Version: 2.1
Name: whatssup
Version: 0.0.5
Summary: What's Sup? - A program control and plugin package for enriching Supervisor
Author: Szasza Palmer
License: MIT License
Project-URL: Repository, https://github.com/Szasza/whatssup.git
Project-URL: Issues, https://github.com/Szasza/whatssup/issues
Keywords: supervisor
Classifier: Development Status :: 2 - Pre-Alpha
Classifier: Environment :: Other Environment
Classifier: Intended Audience :: Developers
Classifier: Intended Audience :: System Administrators
Classifier: License :: OSI Approved :: MIT License
Classifier: Programming Language :: Python :: 3.12
Classifier: Topic :: Software Development :: Libraries :: Python Modules
Classifier: Topic :: System :: Boot
Classifier: Topic :: System :: Monitoring
Classifier: Topic :: System :: Systems Administration
License-File: LICENSE
Requires-Dist: supervisor
